tecton_provider/__init__.py
tecton_provider/example_dags/__init__.py
tecton_provider/example_dags/example_tecton.py
tecton_provider/example_dags/example_tecton_ingest.py
tecton_provider/example_dags/example_tecton_job.py
tecton_provider/example_dags/example_tecton_materialization.py
tecton_provider/example_dags/example_tecton_sensor.py
tecton_provider/hooks/__init__.py
tecton_provider/hooks/tecton_hook.py
tecton_provider/operators/__init__.py
tecton_provider/operators/df_utils.py
tecton_provider/operators/job_utils.py
tecton_provider/operators/tecton_feature_table_ingest_operator.py
tecton_provider/operators/tecton_feature_table_job_operator.py
tecton_provider/operators/tecton_job_operator.py
tecton_provider/operators/tecton_materialization_operator.py
tecton_provider/sensors/__init__.py
tecton_provider/sensors/tecton_sensor.py
tests/__init__.py
tests/hooks/test_tecton_hook.py
tests/operators/test_tecton_feature_table_ingest_operator.py
tests/operators/test_tecton_feature_table_job_operator.py
tests/operators/test_tecton_job_operator.py
tests/operators/test_tecton_materialization_operator.py
tests/sensors/test_tecton_sensor.py
airflow_provider_tecton-0.1.2.dist-info/METADATA
airflow_provider_tecton-0.1.2.dist-info/WHEEL
airflow_provider_tecton-0.1.2.dist-info/entry_points.txt
airflow_provider_tecton-0.1.2.dist-info/top_level.txt
airflow_provider_tecton-0.1.2.dist-info/RECORD
