Metadata-Version: 2.1
Name: airflow-provider-tecton
Version: 0.1.2
Summary: A Tecton provider for Apache Airflow
Home-page: https://github.com/tecton-ai/airflow-provider-tecton
Author: Tecton
Author-email: nacosta@tecton.ai
License: Apache License 2.0
Project-URL: Source Code, https://github.com/tecton-ai/airflow-provider-tecton
Project-URL: Changelog, https://github.com/tecton-ai/airflow-provider-tecton/blob/main/CHANGELOG.md
Project-URL: Bug Tracker, https://github.com/tecton-ai/airflow-provider-tecton/issues
Classifier: Development Status :: 5 - Production/Stable
Classifier: Environment :: Web Environment
Classifier: Framework :: Apache Airflow
Classifier: Framework :: Apache Airflow :: Provider
Classifier: Intended Audience :: Developers
Classifier: License :: OSI Approved :: Apache Software License
Classifier: Operating System :: OS Independent
Classifier: Programming Language :: Python :: 3.8
Classifier: Programming Language :: Python :: 3.9
Classifier: Programming Language :: Python :: 3.10
Classifier: Programming Language :: Python :: 3.11
Requires-Python: >=3.7
Requires-Dist: apache-airflow >=2.0
Requires-Dist: fastparquet
Requires-Dist: pandas
Requires-Dist: pyarrow
Requires-Dist: requests
Provides-Extra: tests
Requires-Dist: mypy ; extra == 'tests'
Requires-Dist: types-requests ; extra == 'tests'
Requires-Dist: parameterized ; extra == 'tests'
Requires-Dist: pytest ; extra == 'tests'
Requires-Dist: pytest-asyncio ; extra == 'tests'
Requires-Dist: pytest-cov ; extra == 'tests'
Requires-Dist: requests-mock ; extra == 'tests'
